MANIFEST.in
README.rst
ez_setup.py
setup.py
GauminIpuinReader.egg-info/PKG-INFO
GauminIpuinReader.egg-info/SOURCES.txt
GauminIpuinReader.egg-info/dependency_links.txt
GauminIpuinReader.egg-info/entry_points.txt
GauminIpuinReader.egg-info/not-zip-safe
GauminIpuinReader.egg-info/requires.txt
GauminIpuinReader.egg-info/top_level.txt
gauminipuinreader/__init__.py
gauminipuinreader/__main__.py
gauminipuinreader/about.rst
gauminipuinreader/main.py
gauminipuinreader/reader.kv
gauminipuinreader/imgs/atea.png
gauminipuinreader/imgs/ej_logo.png
gauminipuinreader/imgs/empty.png
gauminipuinreader/imgs/gaumin_logo.png
gauminipuinreader/imgs/gisa_logo.png
gauminipuinreader/imgs/menu.png
gauminipuinreader/imgs/softboy.png